monascaclient/__init__.py
monascaclient/client.py
monascaclient/shell.py
monascaclient/version.py
monascaclient/common/__init__.py
monascaclient/common/monasca_manager.py
monascaclient/common/utils.py
monascaclient/osc/__init__.py
monascaclient/osc/migration.py
monascaclient/tests/__init__.py
monascaclient/tests/test_client.py
monascaclient/tests/test_shell.py
monascaclient/tests/v2_0/__init__.py
monascaclient/tests/v2_0/shell/__init__.py
monascaclient/tests/v2_0/shell/test_alarm_definitions.py
monascaclient/tests/v2_0/shell/test_metrics.py
monascaclient/tests/v2_0/shell/test_notification_types.py
monascaclient/tests/v2_0/shell/test_notifications.py
monascaclient/v2_0/__init__.py
monascaclient/v2_0/alarm_definitions.py
monascaclient/v2_0/alarms.py
monascaclient/v2_0/client.py
monascaclient/v2_0/metrics.py
monascaclient/v2_0/notifications.py
monascaclient/v2_0/notificationtypes.py
monascaclient/v2_0/shell.py
python_monascaclient-2.8.0.dist-info/AUTHORS
python_monascaclient-2.8.0.dist-info/LICENSE
python_monascaclient-2.8.0.dist-info/METADATA
python_monascaclient-2.8.0.dist-info/WHEEL
python_monascaclient-2.8.0.dist-info/entry_points.txt
python_monascaclient-2.8.0.dist-info/pbr.json
python_monascaclient-2.8.0.dist-info/top_level.txt
python_monascaclient-2.8.0.dist-info/RECORD
